gpxmerge/__init__.py
gpxmerge/gpxmerge.py
gpxmerge-0.0.3.dist-info/LICENSE
gpxmerge-0.0.3.dist-info/METADATA
gpxmerge-0.0.3.dist-info/WHEEL
gpxmerge-0.0.3.dist-info/entry_points.txt
gpxmerge-0.0.3.dist-info/top_level.txt
gpxmerge-0.0.3.dist-info/RECORD
