Metadata-Version: 2.1
Name: gpxmerge
Version: 0.0.3
Summary: GPXMerge
Home-page: https://github.com/rene-d/gpxmerge
Author: rene-d
Author-email: rene.github@gmail.com
License: UNKNOWN
Project-URL: Bug Tracker, https://github.com/rene-d/gpxmerge/issues
Platform: UNKNOWN
Classifier: Programming Language :: Python :: 3
Classifier: License :: Public Domain
Classifier: Operating System :: OS Independent
Requires-Python: >=3.6
License-File: LICENSE
Requires-Dist: simplekml (>=1.3.5)
Requires-Dist: click (>=8.0.0)
Requires-Dist: gpxpy (>=1.4.2)
